vijil/__init__.py
vijil/_client.py
vijil/api.py
vijil/data/detector_list.json
vijil/local_agents/_server.py
vijil/local_agents/constants.py
vijil/local_agents/executor.py
vijil/local_agents/models.py
vijil/templates/vijil_footer.jinja
vijil/templates/vijil_header.jinja
vijil/templates/whole_pdf.jinja
vijil/types.py
vijil/utils.py
vijil-0.1.50.dist-info/METADATA
vijil-0.1.50.dist-info/WHEEL
vijil-0.1.50.dist-info/licenses/LICENSE
vijil-0.1.50.dist-info/RECORD
