Metadata-Version: 2.4
Name: vijil
Version: 0.1.50
Summary: Python Client for Vijil
License-File: LICENSE
Author: Subho Majumdar
Author-email: subho@vijil.ai
Requires-Python: >=3.10,<4.0
Classifier: Programming Language :: Python :: 3
Classifier: Programming Language :: Python :: 3.10
Classifier: Programming Language :: Python :: 3.11
Classifier: Programming Language :: Python :: 3.12
Classifier: Programming Language :: Python :: 3.13
Classifier: Programming Language :: Python :: 3.14
Requires-Dist: bs4 (>=0.0.2,<0.0.3)
Requires-Dist: fastapi (>=0.121.0,<0.122.0)
Requires-Dist: fastparquet (>=2024.5.0,<2025.0.0)
Requires-Dist: mypy (>=1.12.1,<2.0.0)
Requires-Dist: packaging (>=24.2,<25.0)
Requires-Dist: pandas (>=2.1.4,<3.0.0)
Requires-Dist: pyngrok (>=7.2.4,<8.0.0)
Requires-Dist: python-dotenv (>=1.0.1,<2.0.0)
Requires-Dist: requests (>=2.32.3,<3.0.0)
Requires-Dist: starlette (>=0.50.0,<0.51.0)
Requires-Dist: tornado (>=6.5,<7.0)
Requires-Dist: tqdm (>=4.67.1,<5.0.0)
Requires-Dist: types-requests (>=2.32.0.20241016,<3.0.0.0)
Requires-Dist: uvicorn (>=0.34.2,<0.35.0)
Requires-Dist: wakepy (>=0.10.2.post1,<0.11.0)
Requires-Dist: weasyprint (>=65.1,<66.0)
